{
	"users": [{
			"name": ["Jan", "Kowalski"],
			"email": "jan@Kowalski.pl",
			"events": [{
					"id": "1",
					"name": "urodzinki",
					"year": "2017",
					"month": "December",
					"day": "15",
					"description": "urodziny mojego psa"
				}, {
					"id": "2",
					"name": "Test",
					"year": "2018",
					"month": "January",
					"day": "31",
					"description": "kolokwium z angulara"
				},
				{
					"id": "3",
					"name": "lekarz",
					"year": "2018",
					"month": "January",
					"day": "31",
					"description": "wizyta u dentysty"
				}, {
					"id": "4",
					"name": "Test",
					"year": "2018",
					"month": "April",
					"day": "25",
					"description": "kolokwium z matematyki"
				},
				{
					"id": "5",
					"name": "Test",
					"year": "2018",
					"month": "January",
					"day": "29",
					"description": "EGZAMIN !!"
				}
			]
		},
		{
			"name": ["Paweł", "Lewandowski"],
			"email": "pawel@lewandowski.pl",
			"events": [{
				"id": "1",
				"name": "swieta",
				"year": "2018",
				"month": "December",
				"day": "15",
				"description": "przygotowania na swieta"
			}, {
				"id": "2",
				"name": "EGZAMIN",
				"year": "2018",
				"month": "January",
				"day": "20",
				"description": "trzeba sie przygotowac"
			}]
		}
	]
}